towel_foundation/__init__.py
towel_foundation/models.py
towel_foundation/modelview.py
towel_foundation/widgets.py
towel_foundation/locale/de/LC_MESSAGES/django.mo
towel_foundation/locale/de/LC_MESSAGES/django.po
towel_foundation/static/chosen/LICENSE.md
towel_foundation/static/chosen/VERSION
towel_foundation/static/chosen/chosen-sprite.png
towel_foundation/static/chosen/chosen-sprite@2x.png
towel_foundation/static/chosen/chosen.css
towel_foundation/static/chosen/chosen.jquery.min.js
towel_foundation/static/towel_foundation/jquery.elastic.min.js
towel_foundation/static/towel_foundation/towel_foundation.css
towel_foundation/static/towel_foundation/towel_foundation.js
towel_foundation/static/towel_foundation/datepicker/date.js
towel_foundation/static/towel_foundation/datepicker/datePicker.css
towel_foundation/static/towel_foundation/datepicker/jquery.datePicker.js
towel_foundation/templates/404.html
towel_foundation/templates/base.html
towel_foundation/templates/modal.html
towel_foundation/templates/modelview/object_delete_confirmation.html
towel_foundation/templates/modelview/object_detail.html
towel_foundation/templates/modelview/object_form.html
towel_foundation/templates/modelview/object_list.html
towel_foundation/templates/modelview/object_picker.html
towel_foundation/templates/registration/logged_out.html
towel_foundation/templates/registration/login.html
towel_foundation/templates/registration/password_change_done.html
towel_foundation/templates/registration/password_change_form.html
towel_foundation/templates/registration/password_reset_complete.html
towel_foundation/templates/registration/password_reset_confirm.html
towel_foundation/templates/registration/password_reset_done.html
towel_foundation/templates/registration/password_reset_email.html
towel_foundation/templates/registration/password_reset_form.html
towel_foundation/templates/registration/password_reset_subject.txt
towel_foundation/templates/registration/password_set_form.html
towel_foundation-0.30.0.dist-info/LICENSE
towel_foundation-0.30.0.dist-info/METADATA
towel_foundation-0.30.0.dist-info/WHEEL
towel_foundation-0.30.0.dist-info/top_level.txt
towel_foundation-0.30.0.dist-info/RECORD
